{"members_3-ordinarymembers_b84f2246.md":"CR2Bvvps","members_3-ordinarymembers_bili-一只憨憨的小猪.md":"Bcd7acMO","members_3-ordinarymembers_lulu.md":"Fjb2G80O","members_2-importantmembers_bili蓝屏的此电脑.md":"nooEERM1","members_3-ordinarymembers_流焰xwx.md":"Bf4OQrEl","members_2-importantmembers_落雪无痕lxhtt.md":"C-JLfMY5","members_2-importantmembers_苏联球.md":"DkQALg2P","members_3-ordinarymembers_群公用猫娘（属性m.md":"CIxBIcYB","members_1-coremembers_钉佬.md":"KfTPVSsI","members_3-ordinarymembers_在下基岩菌（6年电教）.md":"DEmxzAqJ","members_3-ordinarymembers_mettttro.md":"gH3uTsa4","members_3-ordinarymembers_xhg78999.md":"DXc1J--r","members_3-ordinarymembers_xm137.md":"DSrpmwd3","hof_index.md":"B74xxKNP","members_1-coremembers_小蔡.md":"-ccHyW0_","members_index.md":"Cc2zH6wd","rules_index.md":"DWXfXNOP","members_3-ordinarymembers_1h.md":"li0YqdP0","members_3-ordinarymembers_实名_昵称 姜胤.md":"ClkO_UsP","members_3-ordinarymembers_explorer2.md":"D9-W6r9z","members_1-coremembers_不吃胡萝卜の兔子.md":"Ba5HUeKv","members_2-importantmembers_无名氏.md":"C0tzaY28","members_3-ordinarymembers_jasonwang14250.md":"DDxMDs6w","members_3-ordinarymembers_antarcos.md":"e3RUf8Gs","members_3-ordinarymembers_chenjintang.md":"TM8lg9lS","members_2-importantmembers_文无.md":"DMZbNwct","members_3-ordinarymembers_xiexilin.md":"rsQ7CSev","members_3-ordinarymembers_undefinedfuture.md":"_CEa2sOq","members_3-ordinarymembers_wander@acgurl.link.md":"BW2Vn6fy","members_2-importantmembers_无限进步.md":"BV4p-O41","history_index.md":"D5Vl0jFm","members_3-ordinarymembers_坤坤.md":"BApOKh1H","members_1-coremembers_白熊.md":"BRUqf3lq","members_2-importantmembers_凸(艹皿艹).md":"h4bOEQkh","members_2-importantmembers_群废物管理.md":"D0V5mMkT","members_3-ordinarymembers_pekorabeiwoshi小小柳之絮.md":"D1hsXLY4","members_3-ordinarymembers_wydll(jy).md":"CmQhVcs2","members_3-ordinarymembers_经济是是是.md":"DjHNLo-G","members_3-ordinarymembers_hello8693.md":"DdWEDq9M","members_2-importantmembers_贤狼白子.md":"G3ebxytq","members_3-ordinarymembers_星辰轨迹.md":"DKUqg1tq","members_3-ordinarymembers_催稿催不到真菌.md":"BogSG-h6","members_3-ordinarymembers_张三.md":"DBBzGaI_","aboutus_index.md":"CdHaKHS4","main_index.md":"4Jc7AoRk","members_3-ordinarymembers_博放.md":"BNqAx_Xg","members_2-importantmembers_麒明星.md":"DbXnGfyO","members_3-ordinarymembers_tebot.md":"Bj2PCAwH","members_2-importantmembers_谶无所依.md":"BVK2mqDo","members_1-coremembers_etern.md":"YZJ-kXbO","members_2-importantmembers_yasuyori.md":"C1XBXOVl","index.md":"CTOXwaoD"}
