{"history_index.md":"Dc0lv8sv","members_3-ordinarymembers_1h.md":"BT6UOnGX","main_index.md":"1J6DVuAu","index.md":"ZK0RD599","members_2-importantmembers_无限进步.md":"BE69Ygqc","members_2-importantmembers_文无.md":"nzoedriJ","members_2-importantmembers_麒明星.md":"2gYKVof6","members_1-coremembers_不吃胡萝卜の兔子.md":"BbihD138","members_2-importantmembers_bili蓝屏的此电脑.md":"JjrPeeTy","hof_index.md":"UBlPGqkW","members_2-importantmembers_群废物管理.md":"BVt_aDj3","members_1-coremembers_钉佬.md":"CGDWyPwp","members_2-importantmembers_谶无所依.md":"BmsSom9t","members_3-ordinarymembers_explorer2.md":"BZZJy5kE","members_3-ordinarymembers_lulu.md":"B0ZJvyf5","members_3-ordinarymembers_张三.md":"DT6edfpG","members_3-ordinarymembers_bili-一只憨憨的小猪.md":"DMN4VMuh","aboutus_index.md":"_v51P2fp","members_3-ordinarymembers_实名_昵称 姜胤.md":"YugHhmXV","members_2-importantmembers_凸(艹皿艹).md":"DeCdoHnE","members_3-ordinarymembers_催稿催不到真菌.md":"Di1-E-nT","members_3-ordinarymembers_antarcos.md":"DG5Ad-wG","members_2-importantmembers_贤狼白子.md":"CcSRf2Hu","members_3-ordinarymembers_坤坤.md":"C6IeuFuz","members_3-ordinarymembers_xm137.md":"DW1xGRi2","members_3-ordinarymembers_xiexilin.md":"BaG_w5CS","members_2-importantmembers_yasuyori.md":"B53Td7c4","members_3-ordinarymembers_tebot.md":"D5XUJF7M","members_1-coremembers_白熊.md":"Cj99CrxR","members_2-importantmembers_苏联球.md":"C9REDr7F","members_3-ordinarymembers_星辰轨迹.md":"D9EMogPI","members_3-ordinarymembers_wydll(jy).md":"CFPnxN3N","members_1-coremembers_etern.md":"CTH5Im-X","members_2-importantmembers_落雪无痕lxhtt.md":"DjapwOf8","rules_index.md":"lX18Mgo3","members_1-coremembers_小蔡.md":"CK2l9jGM","members_3-ordinarymembers_pekorabeiwoshi小小柳之絮.md":"Bd7ZUN3f","members_2-importantmembers_无名氏.md":"Bn7EsM84","members_index.md":"B97cKq58","members_3-ordinarymembers_jasonwang14250.md":"B7OpmEPO"}
